odoo/addons/fieldservice_route/README.rst
odoo/addons/fieldservice_route/__init__.py
odoo/addons/fieldservice_route/__manifest__.py
odoo/addons/fieldservice_route/data/fsm_route_day_data.xml
odoo/addons/fieldservice_route/data/fsm_stage_data.xml
odoo/addons/fieldservice_route/data/ir_sequence.xml
odoo/addons/fieldservice_route/i18n/es.po
odoo/addons/fieldservice_route/i18n/es_AR.po
odoo/addons/fieldservice_route/i18n/es_CL.po
odoo/addons/fieldservice_route/i18n/fieldservice_route.pot
odoo/addons/fieldservice_route/i18n/it.po
odoo/addons/fieldservice_route/i18n/pt_BR.po
odoo/addons/fieldservice_route/i18n/pt_PT.po
odoo/addons/fieldservice_route/i18n/tr.po
odoo/addons/fieldservice_route/models/__init__.py
odoo/addons/fieldservice_route/models/fsm_location.py
odoo/addons/fieldservice_route/models/fsm_order.py
odoo/addons/fieldservice_route/models/fsm_route.py
odoo/addons/fieldservice_route/models/fsm_route_day.py
odoo/addons/fieldservice_route/models/fsm_route_dayroute.py
odoo/addons/fieldservice_route/models/fsm_stage.py
odoo/addons/fieldservice_route/readme/CONFIGURE.md
odoo/addons/fieldservice_route/readme/CONTRIBUTORS.md
odoo/addons/fieldservice_route/readme/CREDITS.md
odoo/addons/fieldservice_route/readme/DESCRIPTION.md
odoo/addons/fieldservice_route/readme/USAGE.md
odoo/addons/fieldservice_route/security/ir.model.access.csv
odoo/addons/fieldservice_route/static/description/icon.png
odoo/addons/fieldservice_route/static/description/icon.svg
odoo/addons/fieldservice_route/static/description/index.html
odoo/addons/fieldservice_route/tests/__init__.py
odoo/addons/fieldservice_route/tests/test_fsm_order.py
odoo/addons/fieldservice_route/views/fsm_location.xml
odoo/addons/fieldservice_route/views/fsm_order.xml
odoo/addons/fieldservice_route/views/fsm_route.xml
odoo/addons/fieldservice_route/views/fsm_route_day.xml
odoo/addons/fieldservice_route/views/fsm_route_dayroute.xml
odoo/addons/fieldservice_route/views/menu.xml
odoo_addon_fieldservice_route-18.0.1.0.0.7.dist-info/METADATA
odoo_addon_fieldservice_route-18.0.1.0.0.7.dist-info/WHEEL
odoo_addon_fieldservice_route-18.0.1.0.0.7.dist-info/top_level.txt
odoo_addon_fieldservice_route-18.0.1.0.0.7.dist-info/RECORD
